{"1396144": ["Study of $\\mathbf{B^{0}\\rightarrow\\rho^{+}\\rho^{-}}$ decays and implications for the CKM angle $\\mathbf{\\phi_2}$", "Belle", "10.1103/PhysRevD.93.032010", null, "1510.01245", null, null], "1411223": ["Observation of Zb(10610) and Zb(10650) Decaying to B Mesons", "Belle", "10.1103/PhysRevLett.116.212001", null, "1512.07419", null, null], "1395100": ["Measurement of $D^0 \u2013 \\bar {D^0}$ mixing and search for CP violation in $D^0 \\to K^+ K^\u2212, \\pi^+ \\pi^\u2212$ decays with the full Belle data set", "Belle", "10.1016/j.physletb.2015.12.025", null, "1509.08266", null, null], "1382593": ["Measurement of the branching ratio of $\\bar{B} \\to D^{(\\ast)} \\tau^- \\bar{\\nu}_\\tau$ relative to $\\bar{B} \\to D^{(\\ast)} \\ell^- \\bar{\\nu}_\\ell$ decays with hadronic tagging at Belle", "Belle", "10.1103/PhysRevD.92.072014", null, "1507.03233", null, null], "1391505": ["Inclusive cross sections for pairs of identified light charged hadrons and for single protons in $e^+e^-$ at $\\sqrt{s}=$ 10.58 GeV", "Belle", "10.1103/PhysRevD.92.092007", null, "1509.00563", null, null], "1408873": ["Inclusive and exclusive measurements of $B$ decays to $\\chi_{c1}$ and $\\chi_{c2}$ at Belle", "Belle", "10.1103/PhysRevD.93.052016", null, "1512.02672", null, null], "1373743": ["Measurement of Azimuthal Modulations in the Cross-Section of Di-Pion Pairs in Di-Jet Production from Electron-Positron Annihilation", "Belle", null, null, "1505.08020", null, null], "1336624": ["Measurements of the $\\Upsilon$(10860) and $\\Upsilon$(11020) resonances via $\\sigma(e^+e^-\\to \\Upsilon(nS)\\pi^+ \\pi^-)$", "Belle", "10.1103/PhysRevD.93.011101", null, "1501.01137", null, null], "1369998": ["Study of $D^{**}$ production and light hadronic states in the $\\bar{B}^0 \\to D^{*+} \\omega \\pi^-$ decay", "Belle", "10.1103/PhysRevD.92.012013", null, "1505.03362", null, null], "1408879": ["Search for the rare decay $D^0\\to\\gamma\\gamma$ at Belle", "Belle", "10.1103/PhysRevD.93.051102", null, "1512.02992", null, null], "1358399": ["Semi-inclusive studies of semileptonic $B_s$ decays at Belle", "Belle", "10.1103/PhysRevD.92.072013", null, "1504.02004", null, null], "1341290": ["Observation of X(3872) in B\u2192X(3872)K\u03c0 decays", "Belle", "10.1103/PhysRevD.91.051101", null, "1501.06867", null, null], "1390112": ["Study of $\\pi^0$ pair production in single-tag two-photon collisions", "Belle", "10.1103/PhysRevD.93.032003", null, "1508.06757", "ins1390112", null], "1353536": ["Measurement of the branching fraction of B^+ -> tau^+ nu_tau decays with the semileptonic tagging method", "Belle", "10.1103/PhysRevD.92.051102", null, "1503.05613", null, null], "1408515": ["Observation of the decay $B_s^0\\rightarrow K^0\\overline{K}^0$", "Belle", "10.1103/PhysRevLett.116.161801", null, "1512.02145", null, null], "1341041": ["Search for B decays to final states with the \u03b7$_{c}$ meson", "Belle", "10.1007/JHEP06(2015)132", null, "1501.06351", null, null], "1337783": ["Measurement of the direct $CP$ asymmetry in $\\bar{B}\\rightarrow X_{s+d}\\gamma$ decays with a lepton tag", "Belle", "10.1103/PhysRevLett.114.151601", null, "1501.01702", null, null], "1411075": ["First observation of the decay B$^0\\to \\psi$(2S)$\\pi^0$", "Belle", "10.1103/PhysRevD.93.031101", null, "1512.06895", null, null], "1411218": ["First Observation of Doubly Cabibbo-Suppressed Decay of a Charmed Baryon: $\\Lambda^{+}_{c} \\rightarrow p K^{+} \\pi^{-}$", "Belle", "10.1103/PhysRevLett.117.011801", null, "1512.07366", null, null], "1391645": ["First model-independent Dalitz analysis of $B^0 \\to DK^{*0}$, $D\\to K_S^0\\pi^+\\pi^-$ decay", "Belle", "10.1093/ptep/ptw030", null, "1509.01098", null, null], "1394389": ["Search for $B^0 \\to \\pi^- \\tau^+ \\nu_\\tau$ with hadronic tagging at Belle", "Belle", "10.1103/PhysRevD.93.032007", null, "1509.06521", null, null], "1376480": ["Measurement of $e^+e^- \\to \\gamma\\chi_{cJ}$ via initial state radiation at Belle", "Belle", "10.1103/PhysRevD.92.012011", null, "1506.05229", "ins1376480", null], "1380446": ["First observation of the hadronic transition $ \\Upsilon(4S) \\to \\eta h_{b}(1P)$ and new measurement of the $h_b(1P)$ and $\\eta_b(1S)$ parameters", "Belle", "10.1103/PhysRevLett.115.142001", null, "1506.08914", null, null], "1358936": ["Measurements of $B\\rightarrow \\bar{D} D_{s0} ^{*+}(2317)$ decay rates and a search for isospin partners of the $D_{s0}^{*+} (2317)$", "Belle", "10.1103/PhysRevD.91.092011", null, "1504.02637", null, null], "1347265": ["Search for $B^+ \\to e^+ \\nu$ and $B^+ \\to \\mu^+ \\nu$ decays using hadronic tagging", "Belle", null, null, "1503.01255", null, null], "1357984": ["Evidence for the decay $B^{0} \\to \\eta \\pi^0$", "Belle", "10.1103/PhysRevD.92.011101", null, "1504.00957", null, null], "1346514": ["Measurement of the amplitude ratio of $B^0 \\to D^0K^{*0}$ and $B^0 \\to \\bar{D^0}K^{*0}$ decays with a model-independent Dalitz plot analysis using $D\\to K_S^0\\pi^+\\pi^-$ decays", "Belle", null, null, "1502.07550", null, null], "1370440": ["First Observation of CP Violation in $\\overline{B}^0 \\to D^{(*)}_{\\rm CP} h^0$ Decays by a Combined Time-Dependent Analysis of BABAR and Belle Data", "BaBar", "10.1103/PhysRevLett.115.121604", null, "1505.04147", null, null], "1397632": ["Measurement of the decay $B\\to D\\ell\\nu_\\ell$ in fully reconstructed events and determination of the Cabibbo-Kobayashi-Maskawa matrix element $|V_{cb}|$", "Belle", "10.1103/PhysRevD.93.032006", null, "1510.03657", "ins1397632", ["BELLE_2015_I1397632"]], "1389855": ["Energy scan of the $e^+e^- \\to h_b(nP)\\pi^+\\pi^-$ $(n=1,2)$ cross sections and evidence for $\\Upsilon(11020)$ decays into charged bottomonium-like states", "Belle", "10.1103/PhysRevLett.117.142001", "2047225", "1508.06562", "ins1389855", null], "1342448": ["Search for the decay $B^+\\rightarrow\\overline{K}{}^{*0}K^{*+}$ at Belle", "Belle", "10.1103/PhysRevD.91.071101", null, "1502.00381", null, null], "1364360": ["Search for $B^+ \u2192 \u2113^+\u03bd_\u2113\u03b3$ decays with hadronic tagging using the full Belle data sample", "Belle", "10.1103/PhysRevD.91.112009", null, "1504.05831", null, null], "1392799": ["Observation of $B^{0} \\rightarrow p\\bar{\\Lambda} D^{(*)-}$", "Belle", "10.1103/PhysRevLett.115.221803", null, "1509.03034", null, null]}