{"1312299": ["A Measurement of the $Z^{0}$ Invisible Width by Single-Photon Counting", "OPAL", null, "247687", null, null, null, []], "296526": ["Limits on neutral heavy lepton production from Z0 decay", "OPAL", "10.1016/0370-2693(90)90924-U", "208691", null, null, null, ["CERN-EP-90-72"]], "297895": ["Searches for neutral Higgs bosons in e+ e- collisions at LEP", "OPAL", "10.1007/BF01570792", "210339", null, null, null, ["CERN-EP-90-100"]], "296041": ["Evidence for Final State Photons in Multi - Hadronic Decays of the $\\Z^0$", "OPAL", "10.1016/0370-2693(90)91347-E", "207769", null, null, null, ["CERN-EP-90-55"]], "294809": ["A Study of the Reaction $e^+ e^- \\to \\gamma \\gamma$ at {LEP}", "OPAL", "10.1016/0370-2693(90)91500-B", "205626", null, "ins294809", null, ["CERN-EP-90-29"]], "294808": ["A Combined Analysis of the Hadronic and Leptonic Decays of the $\\Z^0$", "OPAL", "10.1016/0370-2693(90)91137-Z", "205582", null, "ins294808", null, ["CERN-EP-90-27"]], "302586": ["A Direct measurement of the Z0 invisible width by single photon counting", "OPAL", "10.1007/BF01551449", "215182", null, "ins302586", null, ["CERN-PPE-90-187"]], "302587": ["Measurement of the cross-sections of the reactions e+ e- ---> gamma gamma and e+ e- ---> gamma gamma gamma at LEP", "OPAL", "10.1016/0370-2693(91)91932-L", "215195", null, "ins302587", null, ["CERN-PPE-90-189"]], "299833": ["A Study of the recombination scheme dependence of jet production rates and of alpha-s (m(Z0)) in hadronic Z0 decays", "OPAL", "10.1007/BF01549689", "213171", null, "ins299833", null, ["CERN-PPE-90-143"]], "299393": ["Search for pair produced stable singly charged heavy particles in Z0 decays", "OPAL", "10.1016/0370-2693(90)90875-7", "212540", null, null, null, ["CERN-PPE-90-132"]], "299835": ["A Search for lepton flavor violation in Z0 decays", "OPAL", "10.1016/0370-2693(91)90437-U", "213177", null, null, null, ["CERN-PPE-90-148"]], "300283": ["Search for the minimal standard model Higgs boson in e+ e- collisions at LEP", "OPAL", "10.1016/0370-2693(91)91761-J", "213374", null, null, null, ["CERN-PPE-90-150"]], "297562": ["A Direct search for neutralino production at LEP", "OPAL", "10.1016/0370-2693(90)90041-4", "209873", null, null, null, ["CERN-PPE-90-95"]], "297561": ["A Study of angular correlations in 4-jet final states of hadronic Z0 decays", "OPAL", "10.1007/BF01570796", "209887", null, null, null, ["CERN-PPE-90-97"]], "297564": ["A Study of coherence of soft gluons in hadron jets", "OPAL", "10.1016/0370-2693(90)91911-T", "209874", null, "ins297564", null, ["CERN-EP-90-94"]], "294474": ["A Direct Search for New Charged Heavy Leptons at {LEP}", "OPAL", "10.1016/0370-2693(90)90443-A", "204395", null, null, null, ["CERN-EP-90-09"]], "295622": ["Search for Excited Leptons at {LEP}", "OPAL", "10.1016/0370-2693(90)90283-C", "207302", null, null, null, ["CERN-EP-90-49"]], "298642": ["The OPAL detector at LEP", "OPAL", "10.1016/0168-9002(91)90547-4", "211674", null, null, null, ["CERN-PPE-90-114"]], "295407": ["A Search for Technipions and Charged Higgs Bosons at {LEP}", "OPAL", "10.1016/0370-2693(90)91474-P", "206762", null, null, null, ["CERN-EP-90-38"]], "298707": ["A Measurement of energy correlations and a determination of alpha-s (M2 (Z0)) in e+ e- annihilations at s**(1/2) = 91-GeV", "OPAL", "10.1016/0370-2693(90)91098-V", "211675", null, "ins298707", null, ["CERN-PPE-90-121"]], "295613": ["A Measurement of Global Event Shape Distributions in the Hadronic Decays of the $\\Z^0$", "OPAL", "10.1007/BF01552315", "207265", null, "ins295613", null, ["CERN-EP-90-48"]], "297139": ["Analysis of Z0 couplings to charged leptons", "OPAL", "10.1016/0370-2693(90)90925-V", "209485", null, "ins297139", null, ["CERN-EP-90-81"]], "298682": ["Limits on a light Higgs boson in e+ e- collisions at LEP", "OPAL", "10.1016/0370-2693(90)90255-5", "211399", null, null, null, ["CERN-PPE-90-116"]]}