{"528176": ["Measurement of the relative branching fraction of upsilon(4S) to charged and neutral B meson pairs", "CLEO", "10.1103/PhysRevLett.86.2737", null, "hep-ex/0006002", null, null, ["hep-ex/0006002", "SLAC-REPRINT-2000-057", "CLNS-00-1670", "CLEO-00-7"]], "522756": ["Study of two-body B decays to kaons and pions: Observation of B ---> pi+ pi-, B ---> K+- pi0, and B ---> K0 pi0 decays", "CLEO", null, null, "hep-ex/0001010", null, null, ["SLAC-REPRINT-2000-081", "CLNS-99-1650", "CLEO-99-18", "hep-ex/0001010"]], "538110": ["Evidence of new states decaying into Xi-prime(c) pi", "CLEO", "10.1103/PhysRevLett.86.4243", null, "hep-ex/0012020", null, null, ["hep-ex/0012020", "CLNS-00-1702", "CLEO-00-25"]], "537154": ["Dalitz analysis of the decay D0 ---> K- pi+ pi0", "CLEO", "10.1103/PhysRevD.63.092001", null, "hep-ex/0011065", null, null, ["hep-ex/0011065", "CLNS-00-1700", "CLEO-00-23"]], "532734": ["Observation of B --> K+- pi0 and B --> K0 pi0, and evidence for B --> pi+ pi-", "CLEO", "10.1103/PhysRevLett.85.515", null, null, null, null, ["SLAC-REPRINT-2000-061"]], "522755": ["Measurement of charge asymmetries in charmless hadronic in b meson decays", "CLEO", "10.1103/PhysRevLett.85.525", null, "hep-ex/0001009", null, null, ["SLAC-REPRINT-2000-080", "CLNS-99-1651A", "CLEO-99-17", "hep-ex/0001009", "CLNS-99-1651"]], "526928": ["Precise measurement of $B^0 \\bar{B}^0$ mixing parameters at the $\\Upsilon$(4S)", "CLEO", "10.1016/S0370-2693(00)00990-4", null, "hep-ex/0005013", null, null, ["hep-ex/0005013", "SLAC-REPRINT-2000-090", "CLNS-00-1668", "CLEO-00-6"]], "530792": ["Evidence of new states decaying into Xi-prime(c) pi", "CLEO", null, null, "hep-ex/0007050", null, null, ["SLAC-REPRINT-2000-069", "CLEO-CONF-00-5", "ICHEP-00-863", "hep-ex/0007050", "CONF-00-5"]], "535016": ["Study of tau decays to six pions and neutrino", "CLEO", "10.1103/PhysRevLett.86.4467", null, "hep-ex/0010025", null, null, ["hep-ex/0010025", "SLAC-REPRINT-2000-074", "CLNS-00-1687", "CLEO-00-16"]], "530545": ["First observation of the Sigma*+(c) baryon and a new measurement of the Sigma+(c) mass", "CLEO", "10.1103/PhysRevLett.86.1167", null, "hep-ex/0007041", "ins530545", null, ["hep-ex/0007041", "SLAC-REPRINT-2000-064", "CLNS-00-1681", "CLEO-00-13"]], "530791": ["Observation of new states decaying into Lambda(c)+ pi- pi+", "CLEO", null, null, "hep-ex/0007049", null, null, ["SLAC-REPRINT-2000-068", "CLEO-CONF-00-2", "ICHEP-00-862", "hep-ex/0007049"]], "535805": ["Bounds on the CP asymmetry in $b \\to s \\gamma$ decays", "CLEO", "10.1103/PhysRevLett.86.5661", null, "hep-ex/0010075", null, null, ["hep-ex/0010075", "SLAC-REPRINT-2000-078", "CLNS-00-1697", "CLEO-00-21"]], "530546": ["Search for decays of $B^0$ mesons into pairs of leptons: $B^0 \\to e^{+} e^{-}$, $B^0 \\to$ muon+ muon- and $B^0 \\to e^\\pm$ muon-+", "CLEO", "10.1103/PhysRevD.62.091102", null, "hep-ex/0007042", null, null, ["hep-ex/0007042", "SLAC-REPRINT-2000-065", "CLNS-00-1679", "CLEO-00-11"]], "524449": ["Study of the decays $B^0 \\to D^{*}$ + $D^{*-}$", "CLEO", "10.1103/PhysRevD.62.032005", null, "hep-ex/0002065", null, null, ["SLAC-REPRINT-2000-083", "CLNS-00-1663", "CLEO-00-02", "hep-ex/0002065"]], "526692": ["Measurement of the product branching fraction b(c ---> theta(c) X) B(theta(c) ---> Lambda X)", "CLEO", "10.1103/PhysRevD.62.092007", null, "hep-ex/0004033", null, null, ["hep-ex/0004033", "SLAC-REPRINT-2000-089", "CLNS-99-1630", "CLEO-99-10"]], "530957": ["A Search for B ---> tau nu", "CLEO", "10.1103/PhysRevLett.86.2950", null, "hep-ex/0007057", null, null, ["hep-ex/0007057", "SLAC-REPRINT-2000-071", "CLNS-00-1674", "CLEO-00-10"]], "529158": ["Measurements of the mass, total width and two photon partial width of the eta(c) meson", "CLEO", "10.1103/PhysRevLett.85.3095", null, "hep-ex/0006026", null, null, ["hep-ex/0006026", "SLAC-REPRINT-2000-063", "CLNS-00-1673", "CLEO-00-09"]], "536906": ["Measurement of the Lambda+(c) lifetime", "CLEO", "10.1103/PhysRevLett.86.2232", null, "hep-ex/0011049", null, null, ["hep-ex/0011049", "SLAC-REPRINT-2000-093", "CLNS-00-1701", "CLEO-00-24"]], "532904": ["First observation of the decays B0 ---> D*- p anti-p pi+ and B0 ---> D*-p anti-n", "CLEO", "10.1103/PhysRevLett.86.2732", null, "hep-ex/0009011", null, null, ["hep-ex/0009011", "SLAC-REPRINT-2000-073", "CLNS-00-1682", "CLEO-00-14"]], "524526": ["Search for CP violation in $B^\\pm \\to J/\\psi K^\\pm$ and $B^\\pm \\to \\psi_{2S} K^\\pm$ decays", "CLEO", "10.1103/PhysRevLett.84.5940", null, "hep-ex/0003004", null, null, ["hep-ex/0003004", "SLAC-REPRINT-2000-084", "CLNS-00-1661", "CLEO-00-01"]], "530789": ["Observation of the Omega 0(c) charmed baryon at CLEO", "CLEO", null, null, "hep-ex/0007047", null, null, ["SLAC-REPRINT-2000-067", "CLEO-CONF-00-4", "ICHEP-00-999", "hep-ex/0007047"]], "530788": ["Study of (chi(c1) ) and (chi(c2) ) meson production in $B$ meson decays", "CLEO", null, null, "hep-ex/0007046", null, null, ["SLAC-REPRINT-2000-066", "CLEO-CONF-00-6", "ICHEP-00-552", "hep-ex/0007046"]], "530861": ["Determination of the B ---> D* l nu decay width and |V(cb)|", "CLEO", null, null, "hep-ex/0007052", null, null, ["SLAC-REPRINT-2000-070", "CLEO-CONF-00-03", "ICHEP-00-770", "hep-ex/0007052"]], "522777": ["Measurement of the B0 and B+ meson masses from B0 ---> psi(psi-prime) K0(s) and B+ ---> psi(psi-prime) K+ decays", "CLEO", "10.1103/PhysRevD.61.111101", null, "hep-ex/0001013", null, null, ["hep-ex/0001013", "SLAC-REPRINT-2000-082", "CLNS-99-1658", "CLEO-99-22"]], "533916": ["Study of chi(c1) and chi(c2) meson production in $B$ meson decays", "CLEO", "10.1103/PhysRevD.63.031102", null, "hep-ex/0009044", null, null, ["hep-ex/0009044", "SLAC-REPRINT-2000-060", "CLNS-00-1691", "CLEO-00-18"]], "528371": ["Study of charmless hadronic B meson decays to pseudoscalar vector final states", "CLEO", "10.1103/PhysRevLett.85.2881", null, "hep-ex/0006008", null, null, ["hep-ex/0006008", "SLAC-REPRINT-2000-062", "CLNS-99-1652", "CLEO-99-19"]], "526644": ["Study of exclusive two-body $B^0$ meson decays to charmonium", "CLEO", "10.1103/PhysRevD.62.051101", null, "hep-ex/0004032", null, null, ["hep-ex/0004032", "SLAC-REPRINT-2000-088", "CLNS-00-1671", "CLEO-00-8"]], "537236": ["A Measurement of the decay asymmetry parameters in Xi0(c) ---> Xi- pi+", "CLEO", "10.1103/PhysRevD.63.111102", null, "hep-ex/0011073", null, null, ["hep-ex/0011073", "SLAC-REPRINT-2000-094", "CLNS-98-1586", "CLEO-98-15"]], "533575": ["Search for direct CP violation in cascade hyperon decay", "CLEO", null, null, "hep-ex/0009037", null, null, ["hep-ex/0009037", "SLAC-REPRINT-2000-092", "CLNS-98-1587", "CLEO-98-16"]], "526554": ["Measurements of charm fragmentation into D*+(s) and D+(s) in e+ e- annihilations at S**(1/2) = 10.5-GeV", "CLEO", "10.1103/PhysRevD.62.072003", null, "hep-ex/0004028", "ins526554", null, ["hep-ex/0004028", "SLAC-REPRINT-2000-087", "CLNS-00-1667", "CLEO-00-5"]], "529857": ["Study of B decays to charmonium states B ---> eta(c) K and B ---> chi(c0) K", "CLEO", "10.1103/PhysRevLett.86.30", null, "hep-ex/0007012", null, null, ["hep-ex/0007012", "SLAC-REPRINT-2000-058", "CLNS-00-1680", "CLEO-00-12"]], "535988": ["Observation of new states decaying into Lambda+(c) pi- pi+", "CLEO", "10.1103/PhysRevLett.86.4479", null, "hep-ex/0010080", null, null, ["hep-ex/0010080", "SLAC-REPRINT-2000-059", "CLNS-00-1698", "CLEO-00-22"]], "535113": ["Study of $B \\to \\psi_{2S} K$ and $B \\to \\psi_{2S}$ K*(892) decays", "CLEO", "10.1103/PhysRevD.63.031103", null, "hep-ex/0010036", null, null, ["hep-ex/0010036", "SLAC-REPRINT-2000-076", "CLNS-00-1688", "CLEO-00-17"]], "535112": ["Observation of the Omega0(c) charmed baryon at CLEO", "CLEO", "10.1103/PhysRevLett.86.3730", null, "hep-ex/0010035", "ins535112", null, ["hep-ex/0010035", "SLAC-REPRINT-2000-075", "CLNS-00-1695", "CLEO-00-19"]], "539090": ["Search for CP violation in $D^0 \\to K^0_{S} \\pi^0$ and $D^0 \\to \\pi^0 \\pi^0$ and $D^0 \\to K^0_{S} K^0_{S}$ decays", "CLEO", "10.1103/PhysRevD.63.071101", null, "hep-ex/0012054", null, null, ["hep-ex/0012054", "CLNS-00-1708", "CLEO-00-27"]], "525698": ["Resonance structure of tau- ---> K- pi+ pi- nu(tau) decays", "CLEO", "10.1103/PhysRevD.62.072006", null, "hep-ex/0004002", null, null, ["hep-ex/0004002", "SLAC-REPRINT-2000-086", "CLNS-00-1666", "CLEO-00-4"]], "535290": ["Search for a scalar bottom quark with mass 3.5-GeV - 4.5-GeV/c**2", "CLEO", "10.1103/PhysRevD.63.051101", null, "hep-ex/0010047", "ins535290", null, ["hep-ex/0010047", "SLAC-REPRINT-2000-077", "CLNS-00-1696", "CLEO-00-20"]], "531470": ["Measurements of B ---> D(*)(S)+ D+(*) branching fractions", "CLEO", "10.1103/PhysRevD.62.112003", null, "hep-ex/0008015", null, null, ["hep-ex/0008015", "SLAC-REPRINT-2000-072", "CLNS-00-1683", "CLEO-00-15"]], "525697": ["Measurement of B(Lambda+(c) ---> p K- pi+)", "CLEO", "10.1103/PhysRevD.62.072005", null, "hep-ex/0004001", "ins525697", null, ["hep-ex/0004001", "SLAC-REPRINT-2000-085", "CLNS-00-1664", "CLEO-00-3"]], "528729": ["B ---> D* pi+ pi- pi- pi0, D(*) omega pi- and the observation of a wide 1- omega pi- enhancement at 1418-MeV", "CLEO", null, null, "hep-ex/0006018", null, null, ["hep-ex/0006018", "SLAC-REPRINT-2000-091", "CLEO-CONF-00-1"]]}